memengine/__init__.py
memengine/config/Config.py
memengine/config/__init__.py
memengine/function/Encoder.py
memengine/function/Forget.py
memengine/function/Judge.py
memengine/function/LLM.py
memengine/function/Reflector.py
memengine/function/Retrieval.py
memengine/function/Summarizer.py
memengine/function/Trigger.py
memengine/function/Truncation.py
memengine/function/Utilization.py
memengine/function/__init__.py
memengine/memory/BaseMemory.py
memengine/memory/FUMemory.py
memengine/memory/GAMemory.py
memengine/memory/LTMemory.py
memengine/memory/MBMemory.py
memengine/memory/MGMemory.py
memengine/memory/MTMemory.py
memengine/memory/RFMemory.py
memengine/memory/SCMemory.py
memengine/memory/STMemory.py
memengine/memory/__init__.py
memengine/operation/Optimize.py
memengine/operation/Recall.py
memengine/operation/Reflect.py
memengine/operation/Store.py
memengine/operation/__init__.py
memengine/utils/AutoSelector.py
memengine/utils/Client.py
memengine/utils/Display.py
memengine/utils/Storage.py
memengine/utils/__init__.py
memengine-1.1.0.dist-info/METADATA
memengine-1.1.0.dist-info/WHEEL
memengine-1.1.0.dist-info/top_level.txt
memengine-1.1.0.dist-info/RECORD
