Metadata-Version: 2.1
Name: memengine
Version: 1.1.0
Summary: A Comprehensive Library for Memory of LLM-based Agents.
Home-page: https://github.com/nuster1128/MemEngine
Author: Zeyu Zhang
Author-email: zeyuzhang@ruc.edu.cn
Requires-Python: >=3.9
Requires-Dist: langchain>=0.3.3
Requires-Dist: torch>=2.5.1
Requires-Dist: numpy>=1.26.4
Requires-Dist: openai>=1.51.2
Requires-Dist: PyYAML>=6.0.2
Requires-Dist: sentence_transformers>=3.3.1
Requires-Dist: transformers>=4.45.2
